doh/__init__.py
doh/client.py
doh-0.0.1.dist-info/LICENSE
doh-0.0.1.dist-info/METADATA
doh-0.0.1.dist-info/WHEEL
doh-0.0.1.dist-info/top_level.txt
doh-0.0.1.dist-info/RECORD
