Metadata-Version: 2.1
Name: doh
Version: 0.0.1
Summary: A simple, lightweight piece of code to report doh.
Home-page: UNKNOWN
License: UNKNOWN
Platform: UNKNOWN
License-File: LICENSE
Requires-Dist: requests
